{
  "name": "Sayuri Kurata",
  "icon": "https://wiki.gbl.gg/images/d/d2/EFZ_Sayuri_CSS.png",
  "movelists": [
    {
      "name": "Moves",
      "moves": [
        {
          "moveName": "5A",
          "input": "",
          "image": "https://wiki.gbl.gg/images/f/fc/Sayuri5a.png",
          "damage": "200",
          "framedata": {
            "guard": "Ground",
            "startup": "4",
            "active": "5",
            "recovery": "4",
            "advHit": "+2",
            "advBlock": "+1",
            "cancel": "N SP J IC R"
          },
          "properties": [
            "Sayuri does a horizontal chop. An excellent 5A with above average horizontal reach and great frame data. The go-to normal for anti airs after RGing a jump in, as the 4F startup allows the move to beat even 5F jAAA strings if timed well. Can be used in pressure strings to threaten command throw super, works especially well if you cover the first half circle of the super during the animation of 5A."
          ]
        },
        {
          "moveName": "c5B",
          "input": "",
          "image": "https://wiki.gbl.gg/images/thumb/d/d5/Sayuric5b.png/175px-Sayuric5b.png",
          "damage": "410",
          "framedata": {
            "guard": "Low",
            "startup": "6",
            "active": "2",
            "recovery": "20",
            "advHit": "+1",
            "advBlock": "-1",
            "cancel": "N SP J IC f5B 2B"
          },
          "properties": [
            "Sayuri kicks her leg out at a downward angle, hitting the opponent as a low. Excellent move to catch opponents by surprise at max c5B range. Causes a lot of hitstun and blockstun, allowing for easy hitconfirms."
          ]
        },
        {
          "moveName": "f5B",
          "input": "",
          "image": "https://wiki.gbl.gg/images/thumb/f/f4/Sayurif5b.png/175px-Sayurif5b.png",
          "damage": "450",
          "framedata": {
            "guard": "Ground",
            "startup": "8",
            "active": "2",
            "recovery": "14",
            "advHit": "+1",
            "advBlock": "-1",
            "cancel": "N SP IC"
          },
          "properties": [
            "Sayuri swipes with her magical wand. This move has is very disjointed, most characters will have a tough time competing with it. Be careful of opponents with ways to get under this normal, such as slides. Perfect for harassing at a safe range and smacking people out of the air, especially against opponents stuck in the corner. Has a long cancel window. The higher hitbox whiffs on every crouching character."
          ]
        },
        {
          "moveName": "5C",
          "input": "",
          "image": "https://wiki.gbl.gg/images/thumb/a/ac/Sayuri5c.png/175px-Sayuri5c.png",
          "damage": "300",
          "framedata": {
            "guard": "Ground",
            "startup": "10",
            "active": "2",
            "recovery": "/",
            "advHit": "/",
            "advBlock": "/",
            "cancel": "SP IC"
          },
          "properties": [
            "Sayuri's magic wand transforms into a piston which kicks twice. Second hit launches. Has slightly longer range than f5B, making it particularly potent to catch opponents sitting just outside of f5B range. Complements the rest of her neutral buttons but can become dangerous for the player if overused, due to the recovery and extended hurtbox. Short cancel windows makes this difficult to hitconfirm from."
          ],
          "variations": [
            {
              "version": "1st hit",
              "damage": "300",
              "framedata": {
                "guard": "Ground",
                "startup": "10",
                "active": "2",
                "recovery": "/",
                "advHit": "/",
                "advBlock": "/",
                "cancel": "SP IC"
              },
              "notes": "Sayuri's magic wand transforms into a piston which kicks twice. Second hit launches. Has slightly longer range than f5B, making it particularly potent to catch opponents sitting just outside of f5B range. Complements the rest of her neutral buttons but can become dangerous for the player if overused, due to the recovery and extended hurtbox. Short cancel windows makes this difficult to hitconfirm from."
            },
            {
              "version": "2nd hit",
              "damage": "450",
              "framedata": {
                "guard": "Ground",
                "startup": "16",
                "active": "2",
                "recovery": "21",
                "advHit": "/",
                "advBlock": "+2",
                "cancel": "SP IC"
              },
              "notes": "Sayuri's magic wand transforms into a piston which kicks twice. Second hit launches. Has slightly longer range than f5B, making it particularly potent to catch opponents sitting just outside of f5B range. Complements the rest of her neutral buttons but can become dangerous for the player if overused, due to the recovery and extended hurtbox. Short cancel windows makes this difficult to hitconfirm from."
            }
          ]
        },
        {
          "moveName": "2A",
          "input": "",
          "image": "https://wiki.gbl.gg/images/thumb/b/b2/Sayuri2a.png/175px-Sayuri2a.png",
          "damage": "200",
          "framedata": {
            "guard": "Low",
            "startup": "4",
            "active": "4",
            "recovery": "5",
            "advHit": "+2",
            "advBlock": "+1",
            "cancel": "N SP J IC R"
          },
          "properties": [
            "Sayuri extends her arm while crouching. Hits low. A core tool for opening up the opponent. Must be Recoil Guarded low, making it a valuable response after RG. Can be used to threaten command throw super if close to the opponent."
          ]
        },
        {
          "moveName": "2B",
          "input": "",
          "image": "https://wiki.gbl.gg/images/thumb/5/59/Sayuri2b.png/175px-Sayuri2b.png",
          "damage": "430",
          "framedata": {
            "guard": "Ground",
            "startup": "7",
            "active": "8",
            "recovery": "10",
            "advHit": "-1",
            "advBlock": "-3",
            "cancel": "N SP J IC"
          },
          "properties": [
            "Sayuri's wand turns into a sword and she stabs it up and forward. Has almost identical reach to f5B, only with 6 extra active frames and 4 less recovery, at the cost of a more extended hurtbox. As such, it has many of the same uses as f5B, covering slightly different angles. Also has a long cancel window. Be aware that this move will whiff on Nayuki (Asleep) and Ikumi when they are crouching."
          ]
        },
        {
          "moveName": "2C",
          "input": "Active Frame 1",
          "image": "https://wiki.gbl.gg/images/thumb/0/09/Sayuri2c.png/175px-Sayuri2c.png",
          "damage": "600",
          "framedata": {
            "guard": "Ground",
            "startup": "9",
            "active": "9",
            "recovery": "20",
            "advHit": "-5",
            "advBlock": "-7",
            "cancel": "SP JH IC"
          },
          "properties": [
            "Sayuri's wand turns into a mace and she swings it from her feet to above her head. Decent anti-air for opponents too close or too high to use f5B. Active Frames 2-3 Active Frames 4-9",
            "Active Frames 2-3",
            "Active Frames 4-9"
          ]
        },
        {
          "moveName": "j5A",
          "input": "",
          "image": "https://wiki.gbl.gg/images/b/b8/Sayurij5a.png",
          "damage": "200",
          "framedata": {
            "guard": "High/Air",
            "startup": "5",
            "active": "6",
            "recovery": "6",
            "advHit": "/",
            "advBlock": "/",
            "cancel": "N SP J AD IC R"
          },
          "properties": [
            "Sayuri punches diagonally downwards. A core part of Sayuri's mixups and pressure. Can be risky against opponents with a 4F anti-air height 5A if the opponent is good at RG 5A timing."
          ]
        },
        {
          "moveName": "j5B",
          "input": "",
          "image": "https://wiki.gbl.gg/images/thumb/c/c5/Sayurij5b.png/175px-Sayurij5b.png",
          "damage": "430",
          "framedata": {
            "guard": "High/Air",
            "startup": "8",
            "active": "8",
            "recovery": "13",
            "advHit": "-",
            "advBlock": "-",
            "cancel": "N SP J AD IC"
          },
          "properties": [
            "Sayuri extends her leg out in a jumping kick. Excellent priority. Her primary tool for dealing with opponents at the same height in the air. Can be used as a crossup tool but spacing, height and timing is tight."
          ]
        },
        {
          "moveName": "j5C",
          "input": "",
          "image": "https://wiki.gbl.gg/images/thumb/2/25/Sayurij5c.png/175px-Sayurij5c.png",
          "damage": "620",
          "framedata": {
            "guard": "High/Air",
            "startup": "10",
            "active": "2",
            "recovery": "-",
            "advHit": "/",
            "advBlock": "/",
            "cancel": "SP J AD IC"
          },
          "properties": [
            "Sayuri's extends her wand diagonally downwards. One of Sayuri's best normals. Her main normal for getting damage from juggle loops. Your go to air normal when the opponent is below you. Incredible priority."
          ],
          "variations": [
            {
              "version": "Active Frames 1-2",
              "damage": "620",
              "framedata": {
                "guard": "High/Air",
                "startup": "10",
                "active": "2",
                "recovery": "-",
                "advHit": "/",
                "advBlock": "/",
                "cancel": "SP J AD IC"
              },
              "notes": "Sayuri's extends her wand diagonally downwards. One of Sayuri's best normals. Her main normal for getting damage from juggle loops. Your go to air normal when the opponent is below you. Incredible priority."
            },
            {
              "version": "Active Frames 3-12",
              "damage": "550",
              "framedata": {
                "guard": "High/Air",
                "startup": "12",
                "active": "10",
                "recovery": "12",
                "advHit": "/",
                "advBlock": "/",
                "cancel": "SP J AD IC"
              },
              "notes": "Sayuri's extends her wand diagonally downwards. One of Sayuri's best normals. Her main normal for getting damage from juggle loops. Your go to air normal when the opponent is below you. Incredible priority."
            }
          ]
        },
        {
          "moveName": "Ground Throw",
          "input": "Close 6C/4C",
          "image": "https://wiki.gbl.gg/images/a/a4/EFZ_Sayuri_GroundGrab.png",
          "damage": "1150",
          "framedata": {
            "guard": "Throw",
            "startup": "5",
            "active": "1",
            "recovery": "24",
            "advHit": "-",
            "advBlock": "-",
            "cancel": "None"
          },
          "properties": [
            "Sayuri throws the opponent back over her shoulder. This can be both a blessing and a curse - she gets IAD j412C/jC mixups off this, but may lose the corner."
          ]
        },
        {
          "moveName": "Air Throw",
          "input": "Close j6C",
          "image": "https://wiki.gbl.gg/images/a/a8/EFZ_Sayuri_AirGrab.png",
          "damage": "1200",
          "framedata": {
          "guard": "Throw",
          "startup": "2",
          "active": "1",
          "recovery": "/",
          "advHit": "/",
          "advBlock": "/",
          "cancel": "None",
          "property": "I: 3 - 6.66 (on whiff)" 
        },
          "properties": [
            "Sayuri grabs the opponent by the neck and electrocutes them with magic. The invincibility on this air throw starts one frame too late to cover its active frames, meaning it can trade unlike most other throws. On the bright side, these late invincibility frames will cover Sayuri during the startup of her jC if it whiffs, and the invincibility is actually longer than what is usual for throws. As player 2, trading with this can be beneficial thanks to a bug that stuns the opponent in place in the air for 333.33 frames, allowing her to easily start a combo. Throw trades act normally as player 1, making the opponent fall straight to the ground without taking any damage.",
            "The invincibility on this air throw starts one frame too late to cover its active frames, meaning it can trade unlike most other throws. On the bright side, these late invincibility frames will cover Sayuri during the startup of her jC if it whiffs, and the invincibility is actually longer than what is usual for throws.",
            "As player 2, trading with this can be beneficial thanks to a bug that stuns the opponent in place in the air for 333.33 frames, allowing her to easily start a combo. Throw trades act normally as player 1, making the opponent fall straight to the ground without taking any damage."
          ]
        },
        {
          "moveName": "Magical☆Shot",
          "input": "236*",
          "image": "https://wiki.gbl.gg/images/thumb/5/5d/Sayuri236.png/175px-Sayuri236.png",
          "damage": "400",
          "framedata": {
            "guard": "Any",
            "startup": "10.33",
            "active": "∞",
            "recovery": "31.66",
            "advHit": "/",
            "advBlock": "-16",
            "cancel": "FIC"
          },
          "properties": [
            "Sayuri shoots a slow moving star projectile.",
            "Ground versions shoot stars at different heights along the ground.",
            "Air versions shoot stars at different angles.",
            "All versions are easily reacted to in neutral but create pressure opportunities.",
            "B version has better recovery but slightly slower startup.",
            "C version fires both A and B projectiles but costs RF meter."
          ],
          "variations": [
            {
              "version": "A",
              "damage": "400",
              "framedata": {
                "guard": "Any",
                "startup": "10.33",
                "active": "∞",
                "recovery": "31.66",
                "advHit": "/",
                "advBlock": "-16",
                "cancel": "FIC"
              },
              "notes": "Shoots a slow moving star horizontally close to the ground. Easily reacted to in neutral and leaves you open to IAD punishes, but useful to keep opponents guessing."
            },
            {
              "version": "B",
              "damage": "400",
              "framedata": {
                "guard": "Any",
                "startup": "11.33",
                "active": "∞",
                "recovery": "27.66",
                "advHit": "/",
                "advBlock": "-12",
                "cancel": "FIC"
              },
              "notes": "Shoots a slow moving star horizontally at eye height. Slightly safer on block than A version (-12 vs -16) with better recovery but slower startup."
            },
            {
              "version": "C",
              "damage": "400",
              "framedata": {
                "guard": "Any",
                "startup": "7.66",
                "active": "∞",
                "recovery": "37",
                "advHit": "/",
                "advBlock": "-24",
                "cancel": "None"
              },
              "notes": "Sayuri does the A version and B version in quick succession. Not often used as Sayuri has better places to spend RF meter."
            },
            {
              "version": "jA",
              "damage": "400",
              "framedata": {
                "guard": "Any",
                "startup": "14.33",
                "active": "∞",
                "recovery": "36.66",
                "advHit": "/",
                "advBlock": "/",
                "cancel": "FIC"
              },
              "notes": "Shoots a slow moving star directly forward while in the air. Can be used to control horizontal space after an air dash."
            },
            {
              "version": "jB",
              "damage": "400",
              "framedata": {
                "guard": "Any",
                "startup": "14.33",
                "active": "∞",
                "recovery": "36.66",
                "advHit": "/",
                "advBlock": "/",
                "cancel": "FIC"
              },
              "notes": "Shoots a slow moving star angled slightly downward. This projectile does not interact with other projectiles (including Shiori's 5S shield)."
            },
            {
              "version": "jC",
              "damage": "400",
              "framedata": {
                "guard": "Any",
                "startup": "14.33",
                "active": "∞",
                "recovery": "36.66",
                "advHit": "/",
                "advBlock": "/",
                "cancel": "FIC"
              },
              "notes": "Shoots a slow moving star angled more downward than the jB version. Unlike most C specials, this doesn't require RF. Projectile doesn't interact with other projectiles."
            }
          ]
        },
        {
          "moveName": "Magical☆Sword",
          "input": "623*",
          "image": "https://wiki.gbl.gg/images/thumb/2/21/EFZ_Sayuri_623A.png/175px-EFZ_Sayuri_623A.png",
          "damage": "750",
          "framedata": {
            "guard": "Any",
            "startup": "8",
            "active": "2",
            "recovery": "31",
            "advHit": "/",
            "advBlock": "-11",
            "cancel": "IC"
          },
          "properties": [
            "Sayuri transforms her wand into a sword and performs different slash patterns.",
            "A version is a quick horizontal slash that moves Sayuri forward.",
            "B version is a vertical up-then-down slash with poor hitbox placement.",
            "C version combines B version into A version with invulnerability and wallbounce properties.",
            "None of these can be canceled into from normal moves.",
            "A version is especially useful when IC'ed after moves like c5B, f5B, and 2B."
          ],
          "variations": [
            {
              "version": "A",
              "damage": "750",
              "framedata": {
                "guard": "Any",
                "startup": "8",
                "active": "2",
                "recovery": "31",
                "advHit": "/",
                "advBlock": "-11",
                "cancel": "IC"
              },
              "notes": "Quick horizontal slash that moves Sayuri forward. Excellent move with good range and hitbox. Her most common launcher when coupled with IC."
            },
            {
              "version": "B",
              "damage": "500",
              "framedata": {
                "guard": "Any",
                "startup": "10",
                "active": "1",
                "recovery": "47",
                "advHit": "/",
                "advBlock": "-",
                "cancel": "IC"
              },
              "notes": "Vertical up-then-down slash. The first hit won't connect if opponent is standing right next to you. Almost useless with slower startup and easily RGed second hit."
            },
            {
              "version": "B (2nd hit)",
              "damage": "550",
              "framedata": {
                "guard": "Any",
                "startup": "30.66",
                "active": "3",
                "recovery": "24.33",
                "advHit": "/",
                "advBlock": "-5",
                "cancel": "IC"
              },
              "notes": "The downward hit after B version's upward slash. Easily reacted to and RGed if the first hit is blocked or whiffs."
            },
            {
              "version": "C",
              "damage": "400",
              "framedata": {
                "guard": "Any",
                "startup": "14",
                "active": "2",
                "recovery": "68.66",
                "advHit": "/",
                "advBlock": "-",
                "cancel": "IC",
                "property": "I: 0.33-15.66, 55.66-57.33"
              },
              "notes": "First hit of a three-hit sequence (623B + 623A). Has invulnerability on startup. Can be used as a risky reversal option."
            },
            {
              "version": "C (2nd hit)",
              "damage": "550",
              "framedata": {
                "guard": "High, Air",
                "startup": "35.66",
                "active": "3",
                "recovery": "46",
                "advHit": "-",
                "advBlock": "-",
                "cancel": "IC"
              },
              "notes": "Second hit is an overhead that must be blocked high. Part of the C version's three-hit sequence."
            },
            {
              "version": "C (3rd hit)",
              "damage": "500",
              "framedata": {
                "guard": "Any",
                "startup": "57.66",
                "active": "2",
                "recovery": "25",
                "advHit": "-",
                "advBlock": "-12",
                "cancel": "IC"
              },
              "notes": "Final hit of C version's sequence. Will wallbounce the opponent if they are knocked back to the corner."
            }
          ]
        },
        {
          "moveName": "Ah, got your skill~",
          "input": "214A/B/C",
          "image": "https://wiki.gbl.gg/images/f/f3/EFZ_Sayuri_214X_A.png",
          "damage": "600",
          "framedata": {
            "guard": "/",
            "startup": "3",
            "active": "21.33",
            "recovery": "21",
            "advHit": "/",
            "advBlock": "/",
            "cancel": "None"
          },
          "properties": [
            "Sayuri turns around and holds out her hand for a moment.",
            "If Sayuri is attacked by a physical move, she catches the opponent and throws them behind her.",
            "Sayuri will \"remember\" the countered attack for her Magical☆Cutter counter.",
            "As this move doesn't rely on a hitbox, it will successfully counter invincible attacks.",
            "From stand RG, this move allows Sayuri to punish 3.66F gaps or longer.",
            "From crouch RG, this move allows Sayuri to punish 5.66F gaps or longer.",
            "Sayuri can only remember one countered move at a time."
          ],
          "variations": [
            {
              "version": "All",
              "damage": "600",
              "framedata": {
                "guard": "/",
                "startup": "3",
                "active": "21.33",
                "recovery": "21",
                "advHit": "/",
                "advBlock": "/",
                "cancel": "None"
              },
              "notes": "Especially useful against jAA pressure. When combined with Magical☆Cutter, gives Sayuri a strong defensive option that opponents must respect."
            }
          ]
        },
        {
          "moveName": "Magical☆Cutter",
          "input": "Any attack button during the blockstun",
          "image": "https://wiki.gbl.gg/images/thumb/0/0b/EFZ_Sayuri_214X_1.png/175px-EFZ_Sayuri_214X_1.png",
          "damage": "100",
          "framedata": {
            "guard": "Any",
            "startup": "4.33",
            "active": "2",
            "recovery": "56.66",
            "advHit": "/",
            "advBlock": "-39",
            "cancel": "IC",
            "property": "I: 0.33 - 21"
          },
          "properties": [
            "If Sayuri blocks a move previously remembered by \"Ah, got your skill~\", she flashes white during blockstun.",
            "Pressing any attack button during this flash causes her to perform a rising circular kick.",
            "Sayuri is completely invincible while rising up.",
            "This move cannot be buffered, so inputting during blockstop will not work.",
            "Effectiveness depends on what move was caught - quick attacks with short blockstun are harder to react to.",
            "Player 2 Sayuri has a bug allowing her to perform this during captured move's startup if already in blockstun."
          ],
          "variations": [
            {
              "version": "1st hit",
              "damage": "100",
              "framedata": {
                "guard": "Any",
                "startup": "4.33",
                "active": "2",
                "recovery": "56.66",
                "advHit": "/",
                "advBlock": "-39",
                "cancel": "IC"
              },
              "notes": "Initial rising kick that starts the Magical☆Cutter sequence. Completely invincible while rising up."
            },
            {
              "version": "2nd hit",
              "damage": "100",
              "framedata": {
                "guard": "Any", 
                "startup": "6.33",
                "active": "2",
                "recovery": "-",
                "advHit": "/",
                "advBlock": "-",
                "cancel": "IC"
              },
              "notes": "Second hit of the counter sequence. Continues the rising motion with another kick."
            },
            {
              "version": "3rd hit",
              "damage": "100",
              "framedata": {
                "guard": "Any",
                "startup": "8.33",
                "active": "3",
                "recovery": "-",
                "advHit": "/",
                "advBlock": "-",
                "cancel": "IC"
              },
              "notes": "Final hit of the counter sequence with slightly larger hitbox and longer active frames."
            }
          ]
        },
        {
          "moveName": "Magical☆Smash",
          "input": "j412*",
          "image": "https://wiki.gbl.gg/images/thumb/5/5e/Sayurij412.png/175px-Sayurij412.png",
          "damage": "800",
          "framedata": {
            "guard": "Any",
            "startup": "20",
            "active": "Until ground or hit",
            "recovery": "/",
            "advHit": "/",
            "advBlock": "/",
            "cancel": "IC"
          },
          "properties": [
            "Sayuri performs a diagonal downward attack with different properties based on button pressed.",
            "A version is a simple downward attack effective after blocked/RGed aerial attacks.",
            "B version causes Sayuri to jump back if blocked/RGed, allowing for immediate follow-up actions.",
            "C version starts with an invulnerable energy ball phase before the attack.",
            "C version automatically turns around to face the opponent when used as a crossup."
          ],
          "variations": [
                {
                  "version": "A",
                  "damage": "800",
                  "framedata": {
                    "guard": "Any",
                    "startup": "20",
                    "active": "Until ground or hit",
                    "recovery": "/",
                    "advHit": "/",
                    "advBlock": "/",
                    "cancel": "IC"
                  },
                  "notes": "Simple downward strike. When used sparingly, can surprise opponents after a blocked or RGed aerial normal, especially jC. Used in max damage combos."
                },
                {
                  "version": "B",
                  "damage": "500x2",
                  "framedata": {
                    "guard": "Any",
                    "startup": "24",
                    "active": "Until ground or hit",
                    "recovery": "/",
                    "advHit": "/",
                    "advBlock": "/",
                    "cancel": "IC"
                  },
                  "notes": "Sayuri jumps back if this move is blocked or RGed. After this jump back, she can immediately use normals and specials (except j412B). Extremely effective when mixed with j412A."
                },
                {
                  "version": "C (energy ball)",
                  "damage": "400",
                  "framedata": {
                    "guard": "Any",
                    "startup": "3",
                    "active": "36",
                    "recovery": "/",
                    "advHit": "/",
                    "advBlock": "/",
                    "cancel": "IC",
                    "property": "I: 0.33-38.66"
                  },
                  "notes": "Starts with an energy ball phase with 38 frames of invulnerability. Excellent for predicting wakeup reversals. Has 5 vulnerable frames before the attack hitbox appears."
                },
                {
                  "version": "C (smash)",
                  "damage": "400x2",
                  "framedata": {
                    "guard": "Any",
                    "startup": "44",
                    "active": "Until ground or hit",
                    "recovery": "-",
                    "advHit": "-",
                    "advBlock": "-",
                    "cancel": "-"
                  },
                  "notes": "Second phase has a much larger hitbox than A or B versions. When used as a crossup, automatically turns to face the opponent. Excellent mixup tool with invulnerability frames."
                }
              ]
        },
        {
          "moveName": "Magical☆Press",
          "input": "41236*",
          "image": "https://wiki.gbl.gg/images/thumb/8/8c/Sayuri41236.png/175px-Sayuri41236.png",
          "damage": "1000",
          "framedata": {
            "guard": "Ground",
            "startup": "17",
            "active": "12",
            "recovery": "14",
            "advHit": "/",
            "advBlock": "-18",
            "cancel": "IC",
            "property": "I: 0.33-20.66(only C version)"
          },
          "properties": [
            "Sayuri dashes forward to slam opponents into the wall.",
            "Air unblockable, making it excellent in blockstrings and mixups.",
            "A version has short range but is relatively safe on block (-4).",
            "B version goes further but is more negative on block (-10).",
            "C version travels the furthest with wallbounce properties and frame 1 invulnerability."
          ],
          "variations": [
                {
                  "version": "A",
                  "damage": "1000",
                  "framedata": {
                    "guard": "Ground",
                    "startup": "17",
                    "active": "12",
                    "recovery": "14",
                    "advHit": "/",
                    "advBlock": "-4",
                    "cancel": "IC"
                  },
                  "notes": "Dashes forward a short distance. Air unblockable and only -4 on block. Incredible in blockstrings when mixed with 236A/B and 623A, creating varied RG timings that make escape difficult."
                },
                {
                  "version": "B",
                  "damage": "1000",
                  "framedata": {
                    "guard": "Ground",
                    "startup": "17",
                    "active": "18",
                    "recovery": "14",
                    "advHit": "/",
                    "advBlock": "-10",
                    "cancel": "IC",
                    "property": "I: 0.33 - 13.33"
                  },
                  "notes": "Travels further than A version but more negative on block (-10). Can be used at ranges where A would whiff, but requires more caution due to the higher punishment risk."
                },
                {
                  "version": "C",
                  "damage": "1350",
                  "framedata": {
                    "guard": "Ground",
                    "startup": "21",
                    "active": "30",
                    "recovery": "10",
                    "advHit": "/",
                    "advBlock": "-18",
                    "cancel": "IC",
                    "property": "I: 0.33-20.66"
                  },
                  "notes": "Travels furthest with wallbounce properties on hit. Has frame 1 invulnerability, making it a powerful reversal option. Also useful for punishing certain projectiles from mid-range."
                }
              ]
        },
                {
                  "moveName": "Magical☆Agents",
        "input": "236236*",
        "image": "https://wiki.gbl.gg/images/thumb/d/d3/EFZ_Sayuri_236236C.gif/175px-EFZ_Sayuri_236236C.gif",
        "damage": "230x8",
        "framedata": {
          "guard": "Any",
          "startup": "15",
          "active": "1.66",
          "recovery": "204",
          "advHit": "-",
          "advBlock": "-35.66",
          "cancel": "None"
        },
        "properties": [
          "Sayuri summons agent clones that attack the opponent.",
          "A version summons 2 agents and is excellent for Blue IC drain.",
          "B version summons 4 agents and can punish unsafe moves from full screen.",
          "C version summons 6 agents with faster startup for improved long-range punishes."
        ],
        "variations": [
          {
            "version": "A, Sayuri",
            "damage": "230x8",
            "framedata": {
              "guard": "Any",
              "startup": "15",
              "active": "1.66",
              "recovery": "204",
              "advHit": "-",
              "advBlock": "-35.66",
              "cancel": "None"
            },
            "notes": "Sayuri's portion of the attack. Will combo from 5C against most characters. Excellent tool for Blue IC drain."
          },
          {
            "version": "A, Agents",
            "damage": "140x6",
            "framedata": {
              "guard": "Any",
              "startup": "/",
              "active": "※0.66 / 1",
              "recovery": "-",
              "advHit": "-",
              "advBlock": "-",
              "cancel": "-"
            },
            "notes": "The 2 agents' portion of the attack, dealing 140 damage per hit for 6 potential hits. Great combo extender."
          },
          {
            "version": "B",
            "damage": "2857",
            "framedata": {
              "guard": "Any",
              "startup": "16",
              "active": "2x12",
              "recovery": "192",
              "advHit": "-",
              "advBlock": "-14.66",
              "cancel": "None"
            },
            "notes": "Sayuri is assisted by 4 agents. Can be used to punish unsafe moves from full screen. Higher overall damage than A version."
          },
          {
            "version": "C",
            "damage": "3992",
            "framedata": {
              "guard": "Any",
              "startup": "10",
              "active": "2x23",
              "recovery": "221",
              "advHit": "-",
              "advBlock": "-22.66",
              "cancel": "None"
            },
            "notes": "Sayuri is assisted by 6 agents. Much faster startup (10f) than other versions, making it even better for long-range punishes. Highest damage potential."
          }
        ]
        },
                    {
            "moveName": "Magical☆Pressure",
            "input": "214236*",
            "image": "https://wiki.gbl.gg/images/0/09/Sayuri2141236.png",
            "damage": "2221",
            "framedata": {
              "guard": "Ground",
              "startup": "15",
              "active": "12",
              "recovery": "15",
              "advHit": "-",
              "advBlock": "-6",
              "cancel": "IC"
            },
            "properties": [
              "Sayuri dashes forward to slam opponents between walls.",
              "All versions have some invulnerability from frame 1.",
              "A version slams the opponent into one wall, then back into the opposite wall.",
              "B version goes back and forth between walls three times.",
              "C version has the most extended invulnerability frames and greatest damage."
            ],
            "variations": [
              {
                "version": "A",
                "damage": "2221",
                "framedata": {
                  "guard": "Ground",
                  "startup": "15",
                  "active": "12",
                  "recovery": "15",
                  "advHit": "-",
                  "advBlock": "-6",
                  "cancel": "IC"
                },
                "notes": "An extra-powerful version of Magical☆Press. This is Sayuri's highest damage combo ender."
              },
              {
                "version": "B",
                "damage": "3163",
                "framedata": {
                  "guard": "Ground",
                  "startup": "11",
                  "active": "18",
                  "recovery": "15",
                  "advHit": "-",
                  "advBlock": "-12",
                  "cancel": "IC",
                  "property": "I: 0.33 - 13.33"
                },
                "notes": "Same as A except slams the opponent into one wall, then back into the opposite wall. A brief period of invulnerability from frame 1, extending slightly into startup, makes this a decent reversal option if you react to the startup or whiff of an opponent's move during her usual IC points in pressure, or after 236* FIC, but often only if you can reach the opponent during the invulnerability window.."
              },
              {
                "version": "C",
                "damage": "4477",
                "framedata": {
                  "guard": "Ground",
                  "startup": "11",
                  "active": "30",
                  "recovery": "15",
                  "advHit": "-",
                  "advBlock": "-24",
                  "cancel": "IC",
                  "property": "I: 0.33-25.33"
                },
                "notes": "Same as above, except goes back and forth between the walls 3 times. Same startup as B version, but the invulnerability extends significantly further into active frames, making this less risky to use from further away."
              }
            ]
        },
              {
        "moveName": "Magical☆Thunder",
      "input": "6321463214*",
      "image": "https://wiki.gbl.gg/images/thumb/4/46/Sayuri6321463214.png/175px-Sayuri6321463214.png",
      "damage": "2327",
      "framedata": {
        "guard": "Throw",
        "startup": "6.33",
        "active": "1",
        "recovery": "-",
        "advHit": "-",
        "advBlock": "-",
        "cancel": "None"
      },
      "properties": [
        "Sayuri grabs the opponent by the neck and electrocutes them.",
        "A version is jumpable after the super flash and rarely used.",
        "B version is impossible to avoid after super flash with frame 1 invulnerability.",
        "C version is impossible to jump after super flash with highest damage.",
        "Even if the throw is avoided, lightning still activates for additional pressure.",
        "Can be buffered during normals to hide the input (e.g. 5AA 63214[6]3214B)."
      ],
      "variations": [
        {
          "version": "A",
          "damage": "2327",
          "framedata": {
            "guard": "Throw",
            "startup": "6.33",
            "active": "1",
            "recovery": "-",
            "advHit": "-",
            "advBlock": "-",
            "cancel": "None",
            "property": "I: 0.33 - 3, 6.33-7.00"
          },
          "notes": "Sayuri grabs the opponent by the neck and electrocutes them. This version is jumpable after the super flash, making it rarely used compared to other versions."
        },
        {
          "version": "B",
          "damage": "3397",
          "framedata": {
            "guard": "Throw",
            "startup": "3.33",
            "active": "0.33",
            "recovery": "-",
            "advHit": "-",
            "advBlock": "-",
            "cancel": "None",
            "property": "I: 0.33-3.33"
          },
          "notes": "Impossible to avoid after super flash. A crucial part of Sayuri's gameplan, forcing opponents to respect her pressure instead of simply blocking or reacting to overheads."
        },
        {
          "version": "C",
          "damage": "4384",
          "framedata": {
            "guard": "Throw",
            "startup": "0.33",
            "active": "0.33",
            "recovery": "-",
            "advHit": "-",
            "advBlock": "-",
            "cancel": "None",
            "property": "I: 0.33-3.33"
          },
          "notes": "Impossible to jump after super flash. Same applications as B version but with higher damage at lower cost efficiency."
        }
      ]
        },
        {
          "moveName": "Magical☆On Stage",
        "input": "2 5 2A 5 5S",
        "image": "https://wiki.gbl.gg/images/thumb/b/b0/SayuriFM.png/163px-SayuriFM.png",
        "damage": "-",
        "framedata": {
          "guard": "Throw",
          "startup": "25",
          "active": "17",
          "recovery": "19",
          "advHit": "/",
          "advBlock": "/",
          "cancel": "None",
          "property": "I: 0.33 - 44.66"
        },
        "properties": [
          "Sayuri teleports above the opponent and falls on top of them.",
          "An invincible throw that can hit both grounded and aerial opponents.",
          "Can be avoided with some well-timed jumping throw invincibility.",
          "Input requires at least 1 frame of no inputs between 2 and 2A, and between 2A and 5S.",
          "Only available when Sayuri is in Final Memory state (below 1/3 health)."
]
        }
      ]
    }
  ]
}